pyest/__init__.py
pyest/linalg.py
pyest/metrics.py
pyest/particle.py
pyest/tens.py
pyest/utils.py
pyest/filters/GaussianMixtureFilter.py
pyest/filters/Gmkf.py
pyest/filters/Gmukf.py
pyest/filters/KalmanFilter.py
pyest/filters/UnscentedKalmanFilter.py
pyest/filters/__init__.py
pyest/filters/sigma_points.py
pyest/gm/__init__.py
pyest/gm/defaults.py
pyest/gm/gm.py
pyest/gm/main.py
pyest/gm/reduce.py
pyest/gm/split.py
pyest/sensors/FieldOfView.py
pyest/sensors/__init__.py
pyest/sensors/defaults.py
pyest-0.4.0.dist-info/METADATA
pyest-0.4.0.dist-info/WHEEL
pyest-0.4.0.dist-info/licenses/LICENSE.txt
pyest-0.4.0.dist-info/RECORD
