Metadata-Version: 2.4
Name: pyest
Version: 0.4.0
Summary: Adaptive Gaussian Mixture State Estimation
Project-URL: Homepage, https://github.com/scope-lab/pyest
Project-URL: Issues, https://github.com/scope-lab/pyest
Project-URL: Documentation, https://pyest.readthedocs.io/en/latest/
Author: Keith A. LeGrand
License-Expression: MIT
License-File: LICENSE.txt
Keywords: Bayesian filtering,Gaussian mixture,Gaussian splitting,negative information,nonlinear estimation,state estimation,target tracking,uncertainty propagation
Requires-Python: >=3.9
Requires-Dist: cvxopt
Requires-Dist: diskcache
Requires-Dist: fastparquet
Requires-Dist: huggingface-hub
Requires-Dist: jax
Requires-Dist: numba
Requires-Dist: numpy
Requires-Dist: pyarrow
Requires-Dist: scipy
Requires-Dist: shapely
Provides-Extra: examples
Requires-Dist: matplotlib; extra == 'examples'
Requires-Dist: stmint>=1.2.1; extra == 'examples'
Requires-Dist: sympy==1.12; extra == 'examples'
Provides-Extra: test
Requires-Dist: dill; extra == 'test'
Requires-Dist: pytest-benchmark; extra == 'test'
Requires-Dist: pytest-cov; extra == 'test'
